{
    "unlock":false,
    "number":5,
    "tile":[  [1,1,1,1,1,1],
              [1,-1,-1,-1,-1,1],
              [1,1,1,1,1,1],
              [-1,1,1,1,1,-1],
              [1,1,1,1,1,1],
              [-1,1,1,1,1,-1],
              [1,1,1,1,1,1],
              [-1,1,1,1,1,-1],
              [1,1,1,1,1,1]
           ],
    "color":5,
    "localisation":"candy ville",
    "type":"DL",
    "target":{
             "bronze":5000,
             "argent":8000,
             "or":12000,
             "moves":20
    }
}
